hedgehog/__init__.py
hedgehog/utils/__init__.py
hedgehog/utils/asyncio.py
hedgehog/utils/test_utils.py
hedgehog/utils/protobuf/__init__.py
hedgehog/utils/zmq/__init__.py
hedgehog/utils/zmq/async_socket.py
hedgehog/utils/zmq/socket.py
tests/protobuf_tests/__init__.py
tests/protobuf_tests/proto/__init__.py
tests/protobuf_tests/proto/test_pb2.py
hedgehog_utils-0.6.0.dist-info/LICENSE
hedgehog_utils-0.6.0.dist-info/METADATA
hedgehog_utils-0.6.0.dist-info/WHEEL
hedgehog_utils-0.6.0.dist-info/entry_points.txt
hedgehog_utils-0.6.0.dist-info/top_level.txt
hedgehog_utils-0.6.0.dist-info/RECORD
